briertools/__init__.py
briertools/scorers.py
briertools-0.0.3.dist-info/METADATA
briertools-0.0.3.dist-info/WHEEL
briertools-0.0.3.dist-info/top_level.txt
briertools-0.0.3.dist-info/RECORD
