Metadata-Version: 2.4
Name: briertools
Version: 0.0.3
Summary: Mixture of Thresholds based Consequentialist Binary Classifier Evaluation
License: BSD-3-Clause
Requires-Dist: numpy
Requires-Dist: scikit-learn
Requires-Dist: matplotlib
Requires-Dist: scipy
Requires-Dist: matplotcheck
Requires-Dist: pandas
